odoo/addons/agreement_maintenance/README.rst
odoo/addons/agreement_maintenance/__init__.py
odoo/addons/agreement_maintenance/__manifest__.py
odoo/addons/agreement_maintenance/i18n/agreement_maintenance.pot
odoo/addons/agreement_maintenance/i18n/de.po
odoo/addons/agreement_maintenance/models/__init__.py
odoo/addons/agreement_maintenance/models/agreement.py
odoo/addons/agreement_maintenance/models/maintenance_request.py
odoo/addons/agreement_maintenance/readme/CONFIGURE.rst
odoo/addons/agreement_maintenance/readme/CONTRIBUTORS.rst
odoo/addons/agreement_maintenance/readme/CREDITS.rst
odoo/addons/agreement_maintenance/readme/DESCRIPTION.rst
odoo/addons/agreement_maintenance/readme/USAGE.rst
odoo/addons/agreement_maintenance/static/description/icon.png
odoo/addons/agreement_maintenance/static/description/index.html
odoo/addons/agreement_maintenance/views/agreement_view.xml
odoo/addons/agreement_maintenance/views/maintenance_request_view.xml
odoo11_addon_agreement_maintenance-11.0.0.0.1.99.dev6.dist-info/METADATA
odoo11_addon_agreement_maintenance-11.0.0.0.1.99.dev6.dist-info/WHEEL
odoo11_addon_agreement_maintenance-11.0.0.0.1.99.dev6.dist-info/top_level.txt
odoo11_addon_agreement_maintenance-11.0.0.0.1.99.dev6.dist-info/RECORD
